setup.py
cmdman/__init__.py
cmdman/logging.py
cmdman.egg-info/PKG-INFO
cmdman.egg-info/SOURCES.txt
cmdman.egg-info/dependency_links.txt
cmdman.egg-info/top_level.txt