Metadata-Version: 1.1
Name: cmdman
Version: 0.0.3
Summary: Simple command line program wrapper adding debugging arguments.
Home-page: https://github.com/fmichea/cmdman
Author: Franck Michea
Author-email: franck.michea@gmail.com
License: BSD
Platform: UNKNOWN
Classifier: License :: OSI Approved :: BSD License
Classifier: Natural Language :: English
Classifier: Operating System :: POSIX :: Linux
Classifier: Programming Language :: Python :: 2
Classifier: Programming Language :: Python :: 3
Classifier: Programming Language :: Python
